primefeat/__init__.py
primefeat/cli.py
primefeat/compute.py
primefeat/gp.py
primefeat/load.py
primefeat/pca.py
primefeat/plots.py
primefeat/significance.py
primefeat/styles/primefeat.mplstyle
primefeat/styles/primefeat_dark.mplstyle
primefeat/styles/primefeat_presentation.mplstyle
primefeat/templates.py
primefeat-0.0.3.dist-info/WHEEL
primefeat-0.0.3.dist-info/entry_points.txt
primefeat-0.0.3.dist-info/METADATA
primefeat-0.0.3.dist-info/RECORD
