Metadata-Version: 2.3
Name: primefeat
Version: 0.0.3
Summary: A python package for the exploration of primordial features.
Author: Rodrigo Calderon
Author-email: Rodrigo Calderon <calderon.cosmology@gmail.com>
Requires-Dist: getdist>=1.7.4
Requires-Dist: ipykernel>=7.1.0
Requires-Dist: matplotlib>=3.10.8
Requires-Dist: numpy
Requires-Dist: scikit-learn>=1.7.2
Requires-Dist: scipy
Requires-Dist: tqdm>=4.67.1
Requires-Dist: typer>=0.20.0
Requires-Dist: marimo>=0.19.2 ; extra == 'interactive'
Requires-Dist: numba>=0.63.1 ; extra == 'jit'
Requires-Python: >=3.10
Provides-Extra: interactive
Provides-Extra: jit
